conch_pattern/__init__.py
conch_pattern-0.0.1.post3.dist-info/LICENSE
conch_pattern-0.0.1.post3.dist-info/METADATA
conch_pattern-0.0.1.post3.dist-info/WHEEL
conch_pattern-0.0.1.post3.dist-info/top_level.txt
conch_pattern-0.0.1.post3.dist-info/RECORD
